{
  "responseContext": {
    "visitorData": "CgttZzRKUS1CVGw0TSi33My8BjIKCgJVUxIEGgAgFw%3D%3D",
    "serviceTrackingParams": [
      {
        "service": "GFEEDBACK",
        "params": [
          {
            "key": "has_unlimited_entitlement",
            "value": "False"
          },
          {
            "key": "has_premium_lite_entitlement",
            "value": "False"
          },
          {
            "key": "logged_in",
            "value": "0"
          },
          {
            "key": "e",
            "value": "23804281,23813628,23943651,24004644,24077241,24166867,24181174,24241378,24290153,24439361,24548629,24566687,39328397,51010235,51017346,51020570,51025415,51037342,51037353,51050361,51053689,51063643,51087998,51089007,51098299,51111738,51115184,51119594,51124104,51146484,51151423,51152050,51174143,51176511,51178320,51178327,51178340,51178351,51179883,51183910,51193717,51204329,51217504,51222382,51222973,51227037,51228850,51230478,51232636,51237842,51241028,51242448,51248734,51255676,51256074,51256084,51274583,51276557,51276565,51281227,51285717,51287196,51292055,51294322,51296439,51298020,51299710,51299724,51303432,51303667,51303669,51303789,51304155,51304731,51305839,51308709,51310742,51311029,51311040,51313109,51313767,51313802,51318845,51322669,51326932,51327144,51327163,51327184,51327613,51330194,51331481,51331504,51331520,51331529,51331542,51331547,51331554,51331563,51332896,51333543,51333879,51334604,51335392,51335594,51335644,51335928,51337186,51340662,51341226,51341975,51342857,51343368,51344661,51345629,51345919,51346046,51346795,51346808,51346829,51346844,51346853,51346872,51346881,51346896,51347325,51349880,51350816,51351446,51353002,51353231,51353393,51353454,51353498,51353996,51354039,51354114,51355201,51355262,51355275,51355287,51355309,51355316,51355333,51355342,51355679,51357477,51359174,51359179,51360104,51360113,51360128,51360208,51360219,51361727,51361828,51362455,51362643,51362857,51363727,51363732,51363747,51363754,51363763,51363772,51364291,51365346,51365459,51365462,51366423,51366427,51366864,51367487,51367993,51369295,51370263,51370274,51371001,51371008,51371294,51371521,51372970,51374016,51374438,51375168,51375719,51376157,51376330,51376516,51376816,51379211,51379274,51380154,51380376,51380387,51380400,51380597,51380757,51380768,51380783,51380790,51380805,51380812,51380827,51380894,51381276,51381818,51381857,51381974,51383427,51384305,51384391,51384461,51384888,51385023,51385276,51385539,51386156,51386538,51386540,51388999"
          }
        ]
      }
    ],
    "maxAgeSeconds": 7200
  },
  "estimatedResults": "3",
  "contents": {
    "sectionListRenderer": {
      "contents": [
        {
          "shelfRenderer": {
            "content": {
              "horizontalListRenderer": {
                "items": [
                  {
                    "tileRenderer": {
                      "style": "TILE_STYLE_YTLR_DEFAULT",
                      "header": {
                        "tileHeaderRenderer": {
                          "thumbnail": {
                            "thumbnails": [
                              {
                                "url": "https://i.ytimg.com/vi/WeI5s0WiwPc/hqdefault.jpg?sqp=-oaymwEVCMACELQBSFDyq4qpAwcVAACIQhgB&rs=AOn4CLCvs9SfKGZVp20SUdxNOInIyn4H3g",
                                "width": 320,
                                "height": 180
                              }
                            ]
                          },
                          "thumbnailOverlays": [
                            {
                              "thumbnailOverlayTimeStatusRenderer": {
                                "text": {
                                  "accessibility": {
                                    "accessibilityData": {
                                      "label": "3 minutes, 34 seconds"
                                    }
                                  },
                                  "simpleText": "3:34"
                                },
                                "style": "DEFAULT"
                              }
                            }
                          ]
                        }
                      },
                      "metadata": {
                        "tileMetadataRenderer": {
                          "title": {
                            "simpleText": "Best friends"
                          },
                          "lines": [
                            {
                              "lineRenderer": {
                                "items": [
                                  {
                                    "lineItemRenderer": {
                                      "text": {
                                        "runs": [
                                          {
                                            "text": "Ali Haider"
                                          }
                                        ]
                                      }
                                    }
                                  }
                                ]
                              }
                            },
                            {
                              "lineRenderer": {
                                "items": [
                                  {
                                    "lineItemRenderer": {
                                      "text": {
                                        "accessibility": {
                                          "accessibilityData": {
                                            "label": "3 views"
                                          }
                                        },
                                        "simpleText": "3 views"
                                      }
                                    }
                                  },
                                  {
                                    "lineItemRenderer": {
                                      "text": {
                                        "simpleText": "•"
                                      }
                                    }
                                  },
                                  {
                                    "lineItemRenderer": {
                                      "text": {
                                        "simpleText": "5 years ago"
                                      }
                                    }
                                  }
                                ]
                              }
                            }
                          ]
                        }
                      },
                      "onSelectCommand": {
                        "clickTrackingParams": "CAsQhbwCGAAiEwi8tvXf2I2LAxVeksIBHWapI3MyBnNlYXJjaFIJc2RzZGRzZGRkmgEDEPQk",
                        "watchEndpoint": {
                          "videoId": "WeI5s0WiwPc",
                          "playlistId": "RDWeI5s0WiwPc",
                          "params": "qgMJc2RzZGRzZGRkugMLCLmN-OvzqczC5AG6AwsI2rSO5ZXTmrevAbgFAQ%3D%3D",
                          "playerParams": "ygUJc2RzZGRzZGRkoAcB",
                          "loggingContext": {
                            "vssLoggingContext": {
                              "serializedContextData": "Gg1SRFdlSTVzMFdpd1Bj"
                            }
                          },
                          "watchEndpointSupportedOnesieConfig": {
                            "html5PlaybackOnesieConfig": {
                              "commonConfig": {
                                "url": "https://rr3---sn-tt1e7nls.googlevideo.com/initplayback?source=youtube&oeis=1&c=TVHTML5&oad=3200&ovd=3200&oaad=3200&oavd=3200&ocs=700&oewis=1&oputc=1&ofpcc=1&msp=1&odepv=1&id=59e239b345a2c0f7&ip=67.144.118.91&initcwndbps=5770000&mt=1737698453&pxtags=Cg4KAnR4Egg1MTM4MDE1NA&rxtags=Cg4KAnR4Egg1MTM4MDE1Mg%2CCg4KAnR4Egg1MTM4MDE1Mw%2CCg4KAnR4Egg1MTM4MDE1NA%2CCg4KAnR4Egg1MTM4MDE1NQ"
                              }
                            }
                          }
                        }
                      },
                      "trackingParams": "CAsQhbwCGAAiEwi8tvXf2I2LAxVeksIBHWapI3NA94GLrbS2jvFZ",
                      "contentId": "WeI5s0WiwPc",
                      "contentType": "TILE_CONTENT_TYPE_VIDEO",
                      "onLongPressCommand": {
                        "clickTrackingParams": "CAsQhbwCGAAiEwi8tvXf2I2LAxVeksIBHWapI3M=",
                        "showMenuCommand": {
                          "contentId": "WeI5s0WiwPc",
                          "thumbnail": {
                            "thumbnails": [
                              {
                                "url": "https://i.ytimg.com/vi/WeI5s0WiwPc/hqdefault.jpg?sqp=-oaymwEVCMACELQBSFDyq4qpAwcVAACIQhgB&rs=AOn4CLCvs9SfKGZVp20SUdxNOInIyn4H3g",
                                "width": 320,
                                "height": 180
                              }
                            ]
                          },
                          "title": {
                            "simpleText": "Best friends"
                          },
                          "subtitle": {
                            "simpleText": "Ali Haider"
                          },
                          "menu": {
                            "menuRenderer": {
                              "items": [
                                {
                                  "menuNavigationItemRenderer": {
                                    "text": {
                                      "runs": [
                                        {
                                          "text": "Play"
                                        }
                                      ]
                                    },
                                    "navigationEndpoint": {
                                      "clickTrackingParams": "CA0QmvwFGAAiEwi8tvXf2I2LAxVeksIBHWapI3MyBnNlYXJjaFIJc2RzZGRzZGRkmgEDEPQk",
                                      "watchEndpoint": {
                                        "videoId": "WeI5s0WiwPc",
                                        "params": "qgMJc2RzZGRzZGRkugMLCLmN-OvzqczC5AG6AwsI2rSO5ZXTmrevAQ%3D%3D",
                                        "playerParams": "ygUJc2RzZGRzZGRk",
                                        "watchEndpointSupportedOnesieConfig": {
                                          "html5PlaybackOnesieConfig": {
                                            "commonConfig": {
                                              "url": "https://rr3---sn-tt1e7nls.googlevideo.com/initplayback?source=youtube&oeis=1&c=TVHTML5&oad=3200&ovd=3200&oaad=3200&oavd=3200&ocs=700&oewis=1&oputc=1&ofpcc=1&msp=1&odepv=1&id=59e239b345a2c0f7&ip=67.144.118.91&initcwndbps=5770000&mt=1737698453&pxtags=Cg4KAnR4Egg1MTM4MDE1NA&rxtags=Cg4KAnR4Egg1MTM4MDE1Mg%2CCg4KAnR4Egg1MTM4MDE1Mw%2CCg4KAnR4Egg1MTM4MDE1NA%2CCg4KAnR4Egg1MTM4MDE1NQ"
                                            }
                                          }
                                        }
                                      }
                                    },
                                    "trackingParams": "CA0QmvwFGAAiEwi8tvXf2I2LAxVeksIBHWapI3M="
                                  }
                                },
                                {
                                  "menuNavigationItemRenderer": {
                                    "text": {
                                      "runs": [
                                        {
                                          "text": "Go to channel"
                                        }
                                      ]
                                    },
                                    "navigationEndpoint": {
                                      "clickTrackingParams": "CAwQ8sgIGAEiEwi8tvXf2I2LAxVeksIBHWapI3M=",
                                      "browseEndpoint": {
                                        "browseId": "UCgH0YehJw3BeVYkAn9DD6sQ"
                                      }
                                    },
                                    "trackingParams": "CAwQ8sgIGAEiEwi8tvXf2I2LAxVeksIBHWapI3M="
                                  }
                                }
                              ],
                              "trackingParams": "CAsQhbwCGAAiEwi8tvXf2I2LAxVeksIBHWapI3M=",
                              "accessibility": {
                                "accessibilityData": {
                                  "label": "Action menu"
                                }
                              }
                            }
                          }
                        }
                      }
                    }
                  },
                  {
                    "tileRenderer": {
                      "style": "TILE_STYLE_YTLR_DEFAULT",
                      "header": {
                        "tileHeaderRenderer": {
                          "thumbnail": {
                            "thumbnails": [
                              {
                                "url": "https://i.ytimg.com/vi/5IUxTz1-Brk/hqdefault.jpg?sqp=-oaymwEVCMACELQBSFDyq4qpAwcVAACIQhgB&rs=AOn4CLDJrDKPcaopIYW_QhYCKGiuDepECQ",
                                "width": 320,
                                "height": 180
                              }
                            ]
                          },
                          "thumbnailOverlays": [
                            {
                              "thumbnailOverlayTimeStatusRenderer": {
                                "text": {
                                  "accessibility": {
                                    "accessibilityData": {
                                      "label": "26 minutes, 3 seconds"
                                    }
                                  },
                                  "simpleText": "26:03"
                                },
                                "style": "DEFAULT"
                              }
                            }
                          ]
                        }
                      },
                      "metadata": {
                        "tileMetadataRenderer": {
                          "title": {
                            "simpleText": "100 Layers of Food Challenge | Delicious Recipes by DaZaZa Challenge"
                          },
                          "lines": [
                            {
                              "lineRenderer": {
                                "items": [
                                  {
                                    "lineItemRenderer": {
                                      "text": {
                                        "runs": [
                                          {
                                            "text": "Dazaza"
                                          }
                                        ]
                                      }
                                    }
                                  }
                                ]
                              }
                            },
                            {
                              "lineRenderer": {
                                "items": [
                                  {
                                    "lineItemRenderer": {
                                      "badge": {
                                        "metadataBadgeRenderer": {
                                          "style": "BADGE_STYLE_TYPE_SIMPLE",
                                          "label": "New",
                                          "trackingParams": "CAgQpDAYASITCLy29d_YjYsDFV6SwgEdZqkjcw=="
                                        }
                                      }
                                    }
                                  },
                                  {
                                    "lineItemRenderer": {
                                      "text": {
                                        "accessibility": {
                                          "accessibilityData": {
                                            "label": "15K views"
                                          }
                                        },
                                        "simpleText": "15K views"
                                      }
                                    }
                                  },
                                  {
                                    "lineItemRenderer": {
                                      "text": {
                                        "simpleText": "•"
                                      }
                                    }
                                  },
                                  {
                                    "lineItemRenderer": {
                                      "text": {
                                        "simpleText": "5 days ago"
                                      }
                                    }
                                  }
                                ]
                              }
                            }
                          ]
                        }
                      },
                      "onSelectCommand": {
                        "clickTrackingParams": "CAgQpDAYASITCLy29d_YjYsDFV6SwgEdZqkjczIGc2VhcmNoUglzZHNkZHNkZGSaAQMQ9CQ=",
                        "watchEndpoint": {
                          "videoId": "5IUxTz1-Brk",
                          "params": "qgMJc2RzZGRzZGRkugMKCPeBi620to7xWboDCwjatI7lldOat68B",
                          "playerParams": "ygUJc2RzZGRzZGRk",
                          "watchEndpointSupportedOnesieConfig": {
                            "html5PlaybackOnesieConfig": {
                              "commonConfig": {
                                "url": "https://rr3---sn-tt1elnel.googlevideo.com/initplayback?source=youtube&oeis=1&c=TVHTML5&oad=3200&ovd=3200&oaad=3200&oavd=3200&ocs=700&oewis=1&oputc=1&ofpcc=1&msp=1&odepv=1&id=e485314f3d7e06b9&ip=67.144.118.91&initcwndbps=5770000&mt=1737698453&pxtags=Cg4KAnR4Egg1MTM4MDE1NA&rxtags=Cg4KAnR4Egg1MTM4MDE1Mg%2CCg4KAnR4Egg1MTM4MDE1Mw%2CCg4KAnR4Egg1MTM4MDE1NA%2CCg4KAnR4Egg1MTM4MDE1NQ"
                              }
                            }
                          }
                        }
                      },
                      "trackingParams": "CAgQpDAYASITCLy29d_YjYsDFV6SwgEdZqkjc0C5jfjr86nMwuQB",
                      "contentId": "5IUxTz1-Brk",
                      "contentType": "TILE_CONTENT_TYPE_VIDEO",
                      "onLongPressCommand": {
                        "clickTrackingParams": "CAgQpDAYASITCLy29d_YjYsDFV6SwgEdZqkjcw==",
                        "showMenuCommand": {
                          "contentId": "5IUxTz1-Brk",
                          "thumbnail": {
                            "thumbnails": [
                              {
                                "url": "https://i.ytimg.com/vi/5IUxTz1-Brk/hqdefault.jpg?sqp=-oaymwEVCMACELQBSFDyq4qpAwcVAACIQhgB&rs=AOn4CLDJrDKPcaopIYW_QhYCKGiuDepECQ",
                                "width": 320,
                                "height": 180
                              }
                            ]
                          },
                          "title": {
                            "simpleText": "100 Layers of Food Challenge | Delicious Recipes by DaZaZa Challenge"
                          },
                          "subtitle": {
                            "simpleText": "Dazaza"
                          },
                          "menu": {
                            "menuRenderer": {
                              "items": [
                                {
                                  "menuNavigationItemRenderer": {
                                    "text": {
                                      "runs": [
                                        {
                                          "text": "Play"
                                        }
                                      ]
                                    },
                                    "navigationEndpoint": {
                                      "clickTrackingParams": "CAoQmvwFGAAiEwi8tvXf2I2LAxVeksIBHWapI3MyBnNlYXJjaFIJc2RzZGRzZGRkmgEDEPQk",
                                      "watchEndpoint": {
                                        "videoId": "5IUxTz1-Brk",
                                        "params": "qgMJc2RzZGRzZGRkugMKCPeBi620to7xWboDCwjatI7lldOat68B",
                                        "playerParams": "ygUJc2RzZGRzZGRk",
                                        "watchEndpointSupportedOnesieConfig": {
                                          "html5PlaybackOnesieConfig": {
                                            "commonConfig": {
                                              "url": "https://rr3---sn-tt1elnel.googlevideo.com/initplayback?source=youtube&oeis=1&c=TVHTML5&oad=3200&ovd=3200&oaad=3200&oavd=3200&ocs=700&oewis=1&oputc=1&ofpcc=1&msp=1&odepv=1&id=e485314f3d7e06b9&ip=67.144.118.91&initcwndbps=5770000&mt=1737698453&pxtags=Cg4KAnR4Egg1MTM4MDE1NA&rxtags=Cg4KAnR4Egg1MTM4MDE1Mg%2CCg4KAnR4Egg1MTM4MDE1Mw%2CCg4KAnR4Egg1MTM4MDE1NA%2CCg4KAnR4Egg1MTM4MDE1NQ"
                                            }
                                          }
                                        }
                                      }
                                    },
                                    "trackingParams": "CAoQmvwFGAAiEwi8tvXf2I2LAxVeksIBHWapI3M="
                                  }
                                },
                                {
                                  "menuNavigationItemRenderer": {
                                    "text": {
                                      "runs": [
                                        {
                                          "text": "Go to channel"
                                        }
                                      ]
                                    },
                                    "navigationEndpoint": {
                                      "clickTrackingParams": "CAkQ8sgIGAEiEwi8tvXf2I2LAxVeksIBHWapI3M=",
                                      "browseEndpoint": {
                                        "browseId": "UCuChxbHR_TWa2PEaHyG2TkQ"
                                      }
                                    },
                                    "trackingParams": "CAkQ8sgIGAEiEwi8tvXf2I2LAxVeksIBHWapI3M="
                                  }
                                }
                              ],
                              "trackingParams": "CAgQpDAYASITCLy29d_YjYsDFV6SwgEdZqkjcw==",
                              "accessibility": {
                                "accessibilityData": {
                                  "label": "Action menu"
                                }
                              }
                            }
                          }
                        }
                      }
                    }
                  },
                  {
                    "tileRenderer": {
                      "style": "TILE_STYLE_YTLR_DEFAULT",
                      "header": {
                        "tileHeaderRenderer": {
                          "thumbnail": {
                            "thumbnails": [
                              {
                                "url": "https://i.ytimg.com/vi/r25qmVyjmlo/hqdefault.jpg?sqp=-oaymwEvCMACELQBSFDyq4qpAyEVAACIQhgB8AEB-AG2CIACgA-KAgwIABABGFYgVihlMA8=&rs=AOn4CLC3xSzaWCzIkwyy6NIZloiH7TWduA",
                                "width": 320,
                                "height": 180
                              }
                            ]
                          },
                          "thumbnailOverlays": [
                            {
                              "thumbnailOverlayTimeStatusRenderer": {
                                "text": {
                                  "accessibility": {
                                    "accessibilityData": {
                                      "label": "14 seconds"
                                    }
                                  },
                                  "simpleText": "0:14"
                                },
                                "style": "DEFAULT"
                              }
                            }
                          ]
                        }
                      },
                      "metadata": {
                        "tileMetadataRenderer": {
                          "title": {
                            "simpleText": "S oh did dvdudhdvdidcegs ugs didvsushdvzydvdvdh"
                          },
                          "lines": [
                            {
                              "lineRenderer": {
                                "items": [
                                  {
                                    "lineItemRenderer": {
                                      "text": {
                                        "runs": [
                                          {
                                            "text": "Mia tran ᰔᩚᦗꨄ"
                                          }
                                        ]
                                      }
                                    }
                                  }
                                ]
                              }
                            },
                            {
                              "lineRenderer": {
                                "items": [
                                  {
                                    "lineItemRenderer": {
                                      "badge": {
                                        "metadataBadgeRenderer": {
                                          "style": "BADGE_STYLE_TYPE_SIMPLE",
                                          "label": "New",
                                          "trackingParams": "CAUQhbwCGAIiEwi8tvXf2I2LAxVeksIBHWapI3M="
                                        }
                                      }
                                    }
                                  },
                                  {
                                    "lineItemRenderer": {
                                      "text": {
                                        "accessibility": {
                                          "accessibilityData": {
                                            "label": "443 views"
                                          }
                                        },
                                        "simpleText": "443 views"
                                      }
                                    }
                                  },
                                  {
                                    "lineItemRenderer": {
                                      "text": {
                                        "simpleText": "•"
                                      }
                                    }
                                  },
                                  {
                                    "lineItemRenderer": {
                                      "text": {
                                        "simpleText": "3 days ago"
                                      }
                                    }
                                  }
                                ]
                              }
                            }
                          ]
                        }
                      },
                      "onSelectCommand": {
                        "clickTrackingParams": "CAUQhbwCGAIiEwi8tvXf2I2LAxVeksIBHWapI3MyBnNlYXJjaFIJc2RzZGRzZGRkmgEDEPQk",
                        "watchEndpoint": {
                          "videoId": "r25qmVyjmlo",
                          "playlistId": "RDr25qmVyjmlo",
                          "params": "qgMJc2RzZGRzZGRkugMKCPeBi620to7xWboDCwi5jfjr86nMwuQBuAUB",
                          "playerParams": "ygUJc2RzZGRzZGRkoAcB",
                          "loggingContext": {
                            "vssLoggingContext": {
                              "serializedContextData": "Gg1SRHIyNXFtVnlqbWxv"
                            }
                          },
                          "watchEndpointSupportedOnesieConfig": {
                            "html5PlaybackOnesieConfig": {
                              "commonConfig": {
                                "url": "https://rr2---sn-tt1e7nlz.googlevideo.com/initplayback?source=youtube&oeis=1&c=TVHTML5&oad=3200&ovd=3200&oaad=3200&oavd=3200&ocs=700&oewis=1&oputc=1&ofpcc=1&msp=1&odepv=1&id=af6e6a995ca39a5a&ip=67.144.118.91&initcwndbps=5770000&mt=1737698453&pxtags=Cg4KAnR4Egg1MTM4MDE1NA&rxtags=Cg4KAnR4Egg1MTM4MDE1Mg%2CCg4KAnR4Egg1MTM4MDE1Mw%2CCg4KAnR4Egg1MTM4MDE1NA%2CCg4KAnR4Egg1MTM4MDE1NQ"
                              }
                            }
                          }
                        }
                      },
                      "trackingParams": "CAUQhbwCGAIiEwi8tvXf2I2LAxVeksIBHWapI3NA2rSO5ZXTmrevAQ==",
                      "contentId": "r25qmVyjmlo",
                      "contentType": "TILE_CONTENT_TYPE_VIDEO",
                      "onLongPressCommand": {
                        "clickTrackingParams": "CAUQhbwCGAIiEwi8tvXf2I2LAxVeksIBHWapI3M=",
                        "showMenuCommand": {
                          "contentId": "r25qmVyjmlo",
                          "thumbnail": {
                            "thumbnails": [
                              {
                                "url": "https://i.ytimg.com/vi/r25qmVyjmlo/hqdefault.jpg?sqp=-oaymwEvCMACELQBSFDyq4qpAyEVAACIQhgB8AEB-AG2CIACgA-KAgwIABABGFYgVihlMA8=&rs=AOn4CLC3xSzaWCzIkwyy6NIZloiH7TWduA",
                                "width": 320,
                                "height": 180
                              }
                            ]
                          },
                          "title": {
                            "simpleText": "S oh did dvdudhdvdidcegs ugs didvsushdvzydvdvdh"
                          },
                          "subtitle": {
                            "simpleText": "Mia tran ᰔᩚᦗꨄ"
                          },
                          "menu": {
                            "menuRenderer": {
                              "items": [
                                {
                                  "menuNavigationItemRenderer": {
                                    "text": {
                                      "runs": [
                                        {
                                          "text": "Play"
                                        }
                                      ]
                                    },
                                    "navigationEndpoint": {
                                      "clickTrackingParams": "CAcQmvwFGAAiEwi8tvXf2I2LAxVeksIBHWapI3MyBnNlYXJjaFIJc2RzZGRzZGRkmgEDEPQk",
                                      "watchEndpoint": {
                                        "videoId": "r25qmVyjmlo",
                                        "params": "qgMJc2RzZGRzZGRkugMKCPeBi620to7xWboDCwi5jfjr86nMwuQB",
                                        "playerParams": "ygUJc2RzZGRzZGRk",
                                        "watchEndpointSupportedOnesieConfig": {
                                          "html5PlaybackOnesieConfig": {
                                            "commonConfig": {
                                              "url": "https://rr2---sn-tt1e7nlz.googlevideo.com/initplayback?source=youtube&oeis=1&c=TVHTML5&oad=3200&ovd=3200&oaad=3200&oavd=3200&ocs=700&oewis=1&oputc=1&ofpcc=1&msp=1&odepv=1&id=af6e6a995ca39a5a&ip=67.144.118.91&initcwndbps=5770000&mt=1737698453&pxtags=Cg4KAnR4Egg1MTM4MDE1NA&rxtags=Cg4KAnR4Egg1MTM4MDE1Mg%2CCg4KAnR4Egg1MTM4MDE1Mw%2CCg4KAnR4Egg1MTM4MDE1NA%2CCg4KAnR4Egg1MTM4MDE1NQ"
                                            }
                                          }
                                        }
                                      }
                                    },
                                    "trackingParams": "CAcQmvwFGAAiEwi8tvXf2I2LAxVeksIBHWapI3M="
                                  }
                                },
                                {
                                  "menuNavigationItemRenderer": {
                                    "text": {
                                      "runs": [
                                        {
                                          "text": "Go to channel"
                                        }
                                      ]
                                    },
                                    "navigationEndpoint": {
                                      "clickTrackingParams": "CAYQ8sgIGAEiEwi8tvXf2I2LAxVeksIBHWapI3M=",
                                      "browseEndpoint": {
                                        "browseId": "UCawGM_woYS9V0xnWdYbxRdw"
                                      }
                                    },
                                    "trackingParams": "CAYQ8sgIGAEiEwi8tvXf2I2LAxVeksIBHWapI3M="
                                  }
                                }
                              ],
                              "trackingParams": "CAUQhbwCGAIiEwi8tvXf2I2LAxVeksIBHWapI3M=",
                              "accessibility": {
                                "accessibilityData": {
                                  "label": "Action menu"
                                }
                              }
                            }
                          }
                        }
                      }
                    }
                  }
                ],
                "trackingParams": "CAMQxjkiEwi8tvXf2I2LAxVeksIBHWapI3M=",
                "continuations": [
                  {
                    "nextContinuationData": {
                      "continuation": "ElcSCXNkc2Rkc2RkZBpKU0JTQ0FRdFhaVWsxY3pCWGFYZFFZNElCQ3pWSlZYaFVlakV0UW5KcmdnRUxjakkxY1cxV2VXcHRiRy15QVFZS0JBZ0JFQUklM0QYgeDoGA%3D%3D",
                      "clickTrackingParams": "CAQQybcCIhMIvLb139iNiwMVXpLCAR1mqSNz"
                    }
                  }
                ],
                "collapsedItemCount": 3,
                "visibleItemCount": 3
              }
            },
            "trackingParams": "CAIQ3BwYACITCLy29d_YjYsDFV6SwgEdZqkjcw==",
            "headerRenderer": {
              "shelfHeaderRenderer": {
                "avatarLockup": {
                  "avatarLockupRenderer": {
                    "title": {
                      "simpleText": "Search results for sdsddsddd"
                    },
                    "size": "AVATAR_LOCKUP_SIZE_SMALL"
                  }
                }
              }
            },
            "tvhtml5Style": {
              "style": "TV_SHELF_STYLE_DEFAULT",
              "sizeStrategy": "TV_SHELF_SIZE_STRATEGY_FIXED"
            }
          }
        }
      ],
      "trackingParams": "CAEQui8iEwi8tvXf2I2LAxVeksIBHWapI3M="
    }
  },
  "trackingParams": "CAAQvGkiEwi8tvXf2I2LAxVeksIBHWapI3M="
}